{
  "id": "mathematics_hard_04",
  "title": "Hard Mathematics Quiz 4",
  "sections": [
    {
      "title": "Mathematics",
      "items": [
        {
          "type": "multiple-choice",
          "q": "What is d/dx of sin(x)?",
          "a": "cos(x)",
          "options": [
            "-1/x^2",
            "cos(x)",
            "5x^4",
            "e^x"
          ],
          "explanation": "Use standard derivative rules."
        },
        {
          "type": "self-eval",
          "q": "What is the equation of a line with slope 3 and y-intercept -2?",
          "a": "y = 3x - 2",
          "explanation": "Use slope-intercept form y=mx+b."
        },
        {
          "type": "self-eval",
          "q": "Convert 0.125 to a fraction",
          "a": "1/8",
          "explanation": "125/1000 simplifies to 1/8."
        },
        {
          "type": "self-eval",
          "q": "Compute the variance of 1,1,1,1",
          "a": "0",
          "explanation": "All values equal the mean, so spread is zero."
        },
        {
          "type": "true-false",
          "q": "Complex numbers can be represented on a two-dimensional plane.",
          "a": "True",
          "options": [
            "True",
            "False"
          ],
          "explanation": "Real and imaginary parts map to axes."
        },
        {
          "type": "self-eval",
          "q": "What is the probability of rolling a 6 on a fair die?",
          "a": "1/6",
          "explanation": "One favorable outcome out of six."
        },
        {
          "type": "self-eval",
          "q": "What is the binary representation of decimal 10?",
          "a": "1010",
          "explanation": "10 = 8 + 2 in binary places."
        },
        {
          "type": "true-false",
          "q": "A matrix is invertible if and only if its determinant is zero.",
          "a": "False",
          "options": [
            "True",
            "False"
          ],
          "explanation": "Invertible matrices have non-zero determinant."
        },
        {
          "type": "self-eval",
          "q": "How many degrees are in the exterior angle sum of any polygon?",
          "a": "360",
          "explanation": "Exterior angles always sum to 360 degrees."
        },
        {
          "type": "self-eval",
          "q": "If tan(theta)=1, what is theta in degrees in the first quadrant?",
          "a": "45",
          "explanation": "tan 45 degrees equals 1."
        }
      ]
    }
  ]
}
